odoo10_addon_l10n_ch_hr_payroll-10.0.1.0.0.99.dev27-py3.8-nspkg.pth
odoo/addons/l10n_ch_hr_payroll/README.rst
odoo/addons/l10n_ch_hr_payroll/__init__.py
odoo/addons/l10n_ch_hr_payroll/__manifest__.py
odoo/addons/l10n_ch_hr_payroll/data/hr.salary.rule.category.xml
odoo/addons/l10n_ch_hr_payroll/data/hr.salary.rule.xml
odoo/addons/l10n_ch_hr_payroll/i18n/am.po
odoo/addons/l10n_ch_hr_payroll/i18n/ar.po
odoo/addons/l10n_ch_hr_payroll/i18n/bg.po
odoo/addons/l10n_ch_hr_payroll/i18n/bs.po
odoo/addons/l10n_ch_hr_payroll/i18n/ca.po
odoo/addons/l10n_ch_hr_payroll/i18n/ca_ES.po
odoo/addons/l10n_ch_hr_payroll/i18n/cs.po
odoo/addons/l10n_ch_hr_payroll/i18n/da.po
odoo/addons/l10n_ch_hr_payroll/i18n/de.po
odoo/addons/l10n_ch_hr_payroll/i18n/el_GR.po
odoo/addons/l10n_ch_hr_payroll/i18n/en_GB.po
odoo/addons/l10n_ch_hr_payroll/i18n/es.po
odoo/addons/l10n_ch_hr_payroll/i18n/es_AR.po
odoo/addons/l10n_ch_hr_payroll/i18n/es_CO.po
odoo/addons/l10n_ch_hr_payroll/i18n/es_CR.po
odoo/addons/l10n_ch_hr_payroll/i18n/es_DO.po
odoo/addons/l10n_ch_hr_payroll/i18n/es_EC.po
odoo/addons/l10n_ch_hr_payroll/i18n/es_ES.po
odoo/addons/l10n_ch_hr_payroll/i18n/es_MX.po
odoo/addons/l10n_ch_hr_payroll/i18n/es_PE.po
odoo/addons/l10n_ch_hr_payroll/i18n/es_VE.po
odoo/addons/l10n_ch_hr_payroll/i18n/et.po
odoo/addons/l10n_ch_hr_payroll/i18n/eu.po
odoo/addons/l10n_ch_hr_payroll/i18n/fa.po
odoo/addons/l10n_ch_hr_payroll/i18n/fi.po
odoo/addons/l10n_ch_hr_payroll/i18n/fr.po
odoo/addons/l10n_ch_hr_payroll/i18n/fr_CH.po
odoo/addons/l10n_ch_hr_payroll/i18n/gl.po
odoo/addons/l10n_ch_hr_payroll/i18n/gl_ES.po
odoo/addons/l10n_ch_hr_payroll/i18n/he.po
odoo/addons/l10n_ch_hr_payroll/i18n/hr.po
odoo/addons/l10n_ch_hr_payroll/i18n/hr_HR.po
odoo/addons/l10n_ch_hr_payroll/i18n/hu.po
odoo/addons/l10n_ch_hr_payroll/i18n/id.po
odoo/addons/l10n_ch_hr_payroll/i18n/it.po
odoo/addons/l10n_ch_hr_payroll/i18n/ja.po
odoo/addons/l10n_ch_hr_payroll/i18n/ko.po
odoo/addons/l10n_ch_hr_payroll/i18n/l10n_ch_hr_payroll.pot
odoo10_addon_l10n_ch_hr_payroll-10.0.1.0.0.99.dev27.dist-info/METADATA
odoo10_addon_l10n_ch_hr_payroll-10.0.1.0.0.99.dev27.dist-info/WHEEL
odoo10_addon_l10n_ch_hr_payroll-10.0.1.0.0.99.dev27.dist-info/namespace_packages.txt
odoo10_addon_l10n_ch_hr_payroll-10.0.1.0.0.99.dev27.dist-info/top_level.txt
odoo10_addon_l10n_ch_hr_payroll-10.0.1.0.0.99.dev27.dist-info/RECORD
